todict/__init__.py
todict/mixins.py
todict-0.2.4.dist-info/LICENSE
todict-0.2.4.dist-info/METADATA
todict-0.2.4.dist-info/WHEEL
todict-0.2.4.dist-info/top_level.txt
todict-0.2.4.dist-info/RECORD
