Metadata-Version: 2.1
Name: todict
Version: 0.2.4
Summary: Export python objects as dictionnaries so they can then be easily serializable.
Home-page: https://github.com/0livd/python-todict
Author: 0livd
Author-email: UNKNOWN
License: MIT
Platform: UNKNOWN
Classifier: Programming Language :: Python
Classifier: Programming Language :: Python :: 2.7
Classifier: Programming Language :: Python :: 3.6
